lucidate/__init__.py
lucidate/__main__.py
lucidate/cli.py
lucidate/lucidate.py
lucidate-1.0.1.dist-info/METADATA
lucidate-1.0.1.dist-info/WHEEL
lucidate-1.0.1.dist-info/entry_points.txt
lucidate-1.0.1.dist-info/RECORD
